appixer/jlyric/__init__.py
appixer/jlyric/result.py
appixer_jlyric-1.0.1.dist-info/LICENSE
appixer_jlyric-1.0.1.dist-info/METADATA
appixer_jlyric-1.0.1.dist-info/WHEEL
appixer_jlyric-1.0.1.dist-info/top_level.txt
appixer_jlyric-1.0.1.dist-info/RECORD
